setup.py
src/crypto/momentum/trading_client/VERSION
src/crypto/momentum/trading_client/__init__.py
src/crypto/momentum/trading_client/crypto_momentum_trading_client.py
src/crypto_momentum_trading.egg-info/PKG-INFO
src/crypto_momentum_trading.egg-info/SOURCES.txt
src/crypto_momentum_trading.egg-info/dependency_links.txt
src/crypto_momentum_trading.egg-info/requires.txt
src/crypto_momentum_trading.egg-info/top_level.txt