Metadata-Version: 1.2
Name: crypto-momentum-trading
Version: 0.0.1
Summary: A client for trading cryptocurrency with a momentum strategy on the FTX exchange.
Home-page: UNKNOWN
Author: Ryan Krawczyk
Author-email: ryankrawz11@gmail.com
License: UNKNOWN
Platform: UNKNOWN
Classifier: Programming Language :: Python :: 3
Classifier: Operating System :: OS Independent
Requires-Python: >=3.5
